docker_wrap/__init__.py
docker_wrap-0.0.1.data/scripts/docker-wrap
docker_wrap-0.0.1.dist-info/LICENSE
docker_wrap-0.0.1.dist-info/METADATA
docker_wrap-0.0.1.dist-info/WHEEL
docker_wrap-0.0.1.dist-info/top_level.txt
docker_wrap-0.0.1.dist-info/RECORD
