Metadata-Version: 2.1
Name: docker-wrap
Version: 0.0.1
Summary: A drop-in wrapper for docker-compose that runs pre/post scripts
Home-page: https://github.com/jvasile/docker-wrap
Author: James Vasile
Author-email: james@opentechstrategies.com
License: UNKNOWN
Platform: UNKNOWN
Classifier: Programming Language :: Python :: 3
Classifier: License :: OSI Approved :: GNU Affero General Public License v3 or later (AGPLv3+)
Classifier: Operating System :: OS Independent
Requires-Python: >=3.6
